{
  "id": "engineering/Design",
  "title": "Design",
  "description": "Facebook groups / contractors may help here https://www.facebook.com/groups/142661069830141/",
  "source": "@site/src/about/engineering/Design.md",
  "sourceDirName": "engineering",
  "slug": "/engineering/Design",
  "permalink": "/about/engineering/Design",
  "draft": false,
  "unlisted": false,
  "tags": [],
  "version": "current",
  "frontMatter": {},
  "sidebar": "tutorialSidebar",
  "previous": {
    "title": "Cloud Infrastructure",
    "permalink": "/about/engineering/Cloud Infrastructure"
  },
  "next": {
    "title": "Engineering onboarding",
    "permalink": "/about/engineering/Engineering onboarding"
  }
}