{
  "id": "products/web_app/hobbyist-tier/♻️ QR-code generation",
  "title": "♻️ QR-code generation",
  "description": "- This may be useful for Industrial beekeepers with 100 hives that don’t use numeric system or don’t want to search for it in the app.",
  "source": "@site/about/products/web_app/hobbyist-tier/♻️ QR-code generation.md",
  "sourceDirName": "products/web_app/hobbyist-tier",
  "slug": "/products/web_app/hobbyist-tier/♻️ QR-code generation",
  "permalink": "/about/products/web_app/hobbyist-tier/♻️ QR-code generation",
  "draft": false,
  "unlisted": false,
  "tags": [],
  "version": "current",
  "frontMatter": {},
  "sidebar": "tutorialSidebar",
  "previous": {
    "title": "♻️ Public beehive view",
    "permalink": "/about/products/web_app/hobbyist-tier/♻️ Public beehive view"
  },
  "next": {
    "title": "🌻 List local plants",
    "permalink": "/about/products/web_app/hobbyist-tier/🌻 List local plants"
  }
}