{
  "id": "research/Raspberry Pi Bee Health Monitoring Device",
  "title": "Raspberry Pi Bee Health Monitoring Device",
  "description": "PDF",
  "source": "@site/about/research/Raspberry Pi Bee Health Monitoring Device.md",
  "sourceDirName": "research",
  "slug": "/research/Raspberry Pi Bee Health Monitoring Device",
  "permalink": "/about/research/Raspberry Pi Bee Health Monitoring Device",
  "draft": false,
  "unlisted": false,
  "tags": [],
  "version": "current",
  "frontMatter": {
    "title": "Raspberry Pi Bee Health Monitoring Device",
    "orgs": [
      "🇨🇿 Brno University of Technology"
    ],
    "year": "2023"
  },
  "sidebar": "tutorialSidebar",
  "previous": {
    "title": "Markerless tracking of an entire honey bee colony",
    "permalink": "/about/research/Markerless tracking of an entire honey bee colony"
  },
  "next": {
    "title": "Varroa Destructor Classification Using Legendre Fourier Moments with Different Color Spaces",
    "permalink": "/about/research/Varroa Destructor Classification Using Legendre Fourier Moments with Different Color Spaces"
  }
}