{
  "id": "papers/Modular sensory hardware and data processing solution forimplementation of the precision beekeeping",
  "title": "Modular sensory hardware and data processing solution forimplementation of the precision beekeeping",
  "description": "PDF",
  "source": "@site/research/papers/Modular sensory hardware and data processing solution forimplementation of the precision beekeeping.md",
  "sourceDirName": "papers",
  "slug": "/papers/Modular sensory hardware and data processing solution forimplementation of the precision beekeeping",
  "permalink": "/research/papers/Modular sensory hardware and data processing solution forimplementation of the precision beekeeping",
  "draft": false,
  "unlisted": false,
  "tags": [],
  "version": "current",
  "frontMatter": {
    "title": "Modular sensory hardware and data processing solution forimplementation of the precision beekeeping",
    "year": "2019",
    "orgs": [
      "🇱🇻 Latvia University of Life Sciences and Technologies",
      "🇩🇪 University of Kassel"
    ]
  }
}