{
  "id": "Machine Learning/Untitled",
  "title": "Untitled",
  "description": "",
  "source": "@site/docs/Machine Learning/Untitled.md",
  "sourceDirName": "Machine Learning",
  "slug": "/Machine Learning/Untitled",
  "permalink": "/docs/Machine Learning/Untitled",
  "draft": false,
  "unlisted": false,
  "editUrl": "https://github.com/gratheon/website/tree/main/packages/create-docusaurus/templates/shared/docs/Machine Learning/Untitled.md",
  "tags": [],
  "version": "current",
  "frontMatter": {},
  "sidebar": "tutorialSidebar",
  "previous": {
    "title": "Datasets",
    "permalink": "/docs/Machine Learning/Datasets"
  },
  "next": {
    "title": "Robotics",
    "permalink": "/docs/Robotics/"
  }
}